madgrad/__init__.py
madgrad/fairseq_madgrad.py
madgrad/fairseq_mirror_madgrad.py
madgrad/madgrad.py
madgrad/mirror_madgrad.py
madgrad-1.2.dist-info/LICENSE
madgrad-1.2.dist-info/METADATA
madgrad-1.2.dist-info/WHEEL
madgrad-1.2.dist-info/top_level.txt
madgrad-1.2.dist-info/RECORD
