Metadata-Version: 2.1
Name: madgrad
Version: 1.2
Summary: A general purpose PyTorch Optimizer
Home-page: https://github.com/facebookresearch/madgrad
Author: Aaron Defazio
Author-email: adefazio@fb.com
License: UNKNOWN
Platform: UNKNOWN
Classifier: Programming Language :: Python :: 3
Classifier: License :: OSI Approved :: MIT License
Classifier: Operating System :: OS Independent
Requires-Python: >=3.6
License-File: LICENSE
